jira_commonmark/__init__.py
jira_commonmark/api.py
jira_commonmark/converters.py
jira_commonmark/handlers/__init__.py
jira_commonmark/handlers/base.py
jira_commonmark/handlers/commonmarkup.py
jira_commonmark/handlers/html.py
jira_commonmark/handlers/text.py
jira_commonmark/parser.py
jira_commonmark/util.py
jira_commonmark-0.1.8.dist-info/WHEEL
jira_commonmark-0.1.8.dist-info/METADATA
jira_commonmark-0.1.8.dist-info/RECORD
